scriptrunner/__init__.py
scriptrunner/main.py
scriptrunner/assets/ScriptRunner_icon.png
scriptrunner/assets/__init__.py
scriptrunner/lib/__init__.py
scriptrunner/lib/interactions.py
scriptrunner/lib/rendering.py
scriptrunner/lib/utilities.py
scriptrunner_gui-1.0.1.dist-info/licenses/LICENSE
scriptrunner_gui-1.0.1.dist-info/METADATA
scriptrunner_gui-1.0.1.dist-info/WHEEL
scriptrunner_gui-1.0.1.dist-info/entry_points.txt
scriptrunner_gui-1.0.1.dist-info/top_level.txt
scriptrunner_gui-1.0.1.dist-info/RECORD
