Metadata-Version: 2.4
Name: scriptrunner-gui
Version: 1.0.1
Summary: GUI software for rendering arguments of CLI Python scripts and scheduling runs.
Home-page: https://github.com/algotom/scriptrunner
Download-URL: https://github.com/algotom/scriptrunner.git
Author: Nghia Vo
Author-email: nvo@bnl.gov
License: Apache 2.0
Keywords: Script rendering
Platform: Any
Classifier: Programming Language :: Python :: 3
Classifier: License :: OSI Approved :: Apache Software License
Classifier: Intended Audience :: Science/Research
Classifier: Operating System :: OS Independent
Classifier: Natural Language :: English
Classifier: Topic :: Scientific/Engineering
Requires-Python: >=3.9
License-File: LICENSE
Dynamic: author
Dynamic: author-email
Dynamic: classifier
Dynamic: description
Dynamic: description-content-type
Dynamic: download-url
Dynamic: home-page
Dynamic: keywords
Dynamic: license
Dynamic: license-file
Dynamic: platform
Dynamic: requires-python
Dynamic: summary
